onnx_checker/__init__.py
onnx_checker/checker.py
onnx_checker/cli.py
onnx_checker/profiles/KL520.json
onnx_checker/profiles/KL530.json
onnx_checker/profiles/KL630.json
onnx_checker/profiles/KL720.json
onnx_checker/profiles/KL730.json
onnx_checker-0.1.6.dist-info/LICENSE
onnx_checker-0.1.6.dist-info/METADATA
onnx_checker-0.1.6.dist-info/WHEEL
onnx_checker-0.1.6.dist-info/entry_points.txt
onnx_checker-0.1.6.dist-info/RECORD
