Metadata-Version: 2.3
Name: onnx-checker
Version: 0.1.6
Summary: CLI utility to verify operator support before converting ONNX models to Kneron NEF format
License: MIT
Author: Mason Huang
Author-email: masonhuang0320@gmail.com
Requires-Python: >=3.10
Classifier: License :: OSI Approved :: MIT License
Classifier: Programming Language :: Python :: 3
Classifier: Programming Language :: Python :: 3.10
Classifier: Programming Language :: Python :: 3.11
Classifier: Programming Language :: Python :: 3.12
Classifier: Programming Language :: Python :: 3.13
Requires-Dist: onnx (>=1.17.0,<2.0.0)
